camoufox_captcha/__init__.py
camoufox_captcha/cloudflare/__init__.py
camoufox_captcha/cloudflare/solve_by_click.py
camoufox_captcha/cloudflare/utils/__init__.py
camoufox_captcha/cloudflare/utils/detection.py
camoufox_captcha/cloudflare/utils/dom_helpers.py
camoufox_captcha/common/__init__.py
camoufox_captcha/common/detection.py
camoufox_captcha/common/shadow_root.py
camoufox_captcha-0.1.3.dist-info/licenses/LICENSE
camoufox_captcha-0.1.3.dist-info/METADATA
camoufox_captcha-0.1.3.dist-info/WHEEL
camoufox_captcha-0.1.3.dist-info/top_level.txt
camoufox_captcha-0.1.3.dist-info/RECORD
