Metadata-Version: 2.4
Name: camoufox-captcha
Version: 0.1.3
Summary: Automatic captcha solving using Camoufox
Author-email: techinz <contact@techinz.dev>
License-Expression: MIT
Project-URL: Homepage, https://github.com/techinz/camoufox-captcha
Project-URL: Repository, https://github.com/techinz/camoufox-captcha
Project-URL: Issues, https://github.com/techinz/camoufox-captcha/issues
Requires-Python: >=3.8
License-File: LICENSE
Provides-Extra: dev
Requires-Dist: pytest>=8.4.0; extra == "dev"
Requires-Dist: pytest-asyncio>=1.0.0; extra == "dev"
Requires-Dist: pytest-cov>=6.1.1; extra == "dev"
Dynamic: license-file
